                         {
  "id": "0,294,327",
  "slug": "about-mcf/rajbhasha",
  "title": "Rajbhasha",
  "lang": "en",
  "lastReviewed": null,
  "contentHtml": "<style>\n.rajbhasha-section {\n  margin-top: 1rem;\n}\n.rajbhasha-title {\n  font-size: 1.1rem;\n  font-weight: 600;\n  color: #1e3a5f;\n  margin-bottom: 0.75rem;\n  padding-bottom: 0.35rem;\n  border-bottom: 2px solid #0066cc;\n  display: inline-block;\n}\n.rajbhasha-card {\n  display: flex;\n  align-items: center;\n  padding: 0.6rem 0.75rem;\n  background: linear-gradient(135deg, #ffffff 0%, #f8f9fa 100%);\n  border-radius: 6px;\n  border: 1px solid #e2e8f0;\n  text-decoration: none;\n  transition: all 0.3s cubic-bezier(0.4, 0, 0.2, 1);\n  margin-bottom: 0.4rem;\n  box-shadow: 0 1px 3px rgba(0, 0, 0, 0.04);\n}\n.rajbhasha-card:hover {\n  background: linear-gradient(135deg, #f0f7ff 0%, #e2e8f0 100%);\n  border-color: #0066cc;\n  transform: translateX(3px);\n  box-shadow: 0 3px 10px rgba(0, 102, 204, 0.12);\n}\n.rajbhasha-icon {\n  width: 28px;\n  height: 28px;\n  background: linear-gradient(135deg, #0066cc 0%, #004499 100%);\n  border-radius: 5px;\n  display: flex;\n  align-items: center;\n  justify-content: center;\n  font-size: 0.85rem;\n  margin-right: 0.6rem;\n  flex-shrink: 0;\n}\n.rajbhasha-card:hover .rajbhasha-icon {\n  transform: scale(1.05);\n}\n.rajbhasha-content {\n  flex: 1;\n}\n.rajbhasha-card strong {\n  color: #1e3a5f;\n  font-size: 0.85rem;\n  transition: color 0.2s ease;\n}\n.rajbhasha-card:hover strong {\n  color: #0066cc;\n}\n.rajbhasha-arrow {\n  color: #94a3b8;\n  font-size: 0.85rem;\n  margin-left: 0.5rem;\n  transition: all 0.3s ease;\n}\n.rajbhasha-card:hover .rajbhasha-arrow {\n  color: #0066cc;\n  transform: translateX(3px);\n}\n</style>\n\n<div class=\"rajbhasha-section\">\n  <h2 class=\"rajbhasha-title\">Rajbhasha Documents</h2>\n  \n  <a href=\"https://mcf.indianrailways.gov.in/works/uploads/File/Rajbhasha%20Niti%202018-19(1).pdf\" target=\"_blank\" rel=\"noopener noreferrer\" class=\"rajbhasha-card\">\n    <div class=\"rajbhasha-icon\">📄</div>\n    <div class=\"rajbhasha-content\">\n      <strong>Rajbhasha Niti</strong>\n    </div>\n    <span class=\"rajbhasha-arrow\">→</span>\n  </a>\n  \n  <a href=\"https://mcf.indianrailways.gov.in/uploads/files/September%202019.pdf\" target=\"_blank\" rel=\"noopener noreferrer\" class=\"rajbhasha-card\">\n    <div class=\"rajbhasha-icon\">📄</div>\n    <div class=\"rajbhasha-content\">\n      <strong>Pratibimb Railway Booklet-1</strong>\n    </div>\n    <span class=\"rajbhasha-arrow\">→</span>\n  </a>\n  \n  <a href=\"https://mcf.indianrailways.gov.in/uploads/files/September%202020.pdf\" target=\"_blank\" rel=\"noopener noreferrer\" class=\"rajbhasha-card\">\n    <div class=\"rajbhasha-icon\">📄</div>\n    <div class=\"rajbhasha-content\">\n      <strong>Pratibimb Railway Booklet-2</strong>\n    </div>\n    <span class=\"rajbhasha-arrow\">→</span>\n  </a>\n  \n  <a href=\"https://mcf.indianrailways.gov.in/uploads/%E0%A4%AA%E0%A5%8D%E0%A4%B0%E0%A4%97%E0%A4%A4%E0%A4%BF%20%E0%A4%AA%E0%A4%A4%E0%A5%8D%E0%A4%B0%E0%A4%BF%E0%A4%95%E0%A4%BE%20%E0%A4%B8%E0%A4%BF%E0%A4%A4%E0%A4%82%E0%A4%AC%E0%A4%B0%202024.pdf\" target=\"_blank\" rel=\"noopener noreferrer\" class=\"rajbhasha-card\">\n    <div class=\"rajbhasha-icon\">📄</div>\n    <div class=\"rajbhasha-content\">\n      <strong>Pragati Patrika</strong>\n    </div>\n    <span class=\"rajbhasha-arrow\">→</span>\n  </a>\n  \n  <a href=\"https://mcf.indianrailways.gov.in/uploads/MCF%20Pragati%20June-24.pdf\" target=\"_blank\" rel=\"noopener noreferrer\" class=\"rajbhasha-card\">\n    <div class=\"rajbhasha-icon\">📄</div>\n    <div class=\"rajbhasha-content\">\n      <strong>Pragati patrika June 2024</strong>\n    </div>\n    <span class=\"rajbhasha-arrow\">→</span>\n  </a>\n  \n  <a href=\"https://mcf.indianrailways.gov.in/uploads/%E0%A4%AA%E0%A5%8D%E0%A4%B0%E0%A4%97%E0%A4%A4%E0%A4%BF%20%E0%A4%AA%E0%A4%A4%E0%A5%8D%E0%A4%B0%E0%A4%BF%E0%A4%95%E0%A4%BE%20%20%E0%A4%A6%E0%A4%BF%E0%A4%B8%E0%A4%82%E0%A4%AC%E0%A4%B0-2024.pdf\" target=\"_blank\" rel=\"noopener noreferrer\" class=\"rajbhasha-card\">\n    <div class=\"rajbhasha-icon\">📄</div>\n    <div class=\"rajbhasha-content\">\n      <strong>Pragati patrika Dec 2024</strong>\n    </div>\n    <span class=\"rajbhasha-arrow\">→</span>\n  </a>\n  \n  <a href=\"https://mcf.indianrailways.gov.in/uploads/%E0%A4%AE%E0%A4%BE%E0%A4%B0%E0%A5%8D%E0%A4%9A-2025%20%E0%A4%AA%E0%A5%8D%E0%A4%B0%E0%A4%97%E0%A4%A4%E0%A4%BF%20%E0%A4%AA%E0%A4%A4%E0%A5%8D%E0%A4%B0%E0%A4%BF%E0%A4%95%E0%A4%BE(1).pdf\" target=\"_blank\" rel=\"noopener noreferrer\" class=\"rajbhasha-card\">\n    <div class=\"rajbhasha-icon\">📄</div>\n    <div class=\"rajbhasha-content\">\n      <strong>Pragati patrika March 2025</strong>\n    </div>\n    <span class=\"rajbhasha-arrow\">→</span>\n  </a>\n  \n  <a href=\"https://mcf.indianrailways.gov.in/uploads/%E0%A4%AA%E0%A5%8D%E0%A4%B0%E0%A4%97%E0%A4%A4%E0%A4%BF%20%E0%A4%AA%E0%A4%A4%E0%A5%8D%E0%A4%B0%E0%A4%BF%E0%A4%95%E0%A4%BE%20%E0%A4%9C%E0%A5%82%E0%A4%A8-2025.pdf\" target=\"_blank\" rel=\"noopener noreferrer\" class=\"rajbhasha-card\">\n    <div class=\"rajbhasha-icon\">📄</div>\n    <div class=\"rajbhasha-content\">\n      <strong>Pragati patrika June 2025</strong>\n    </div>\n    <span class=\"rajbhasha-arrow\">→</span>\n  </a>\n  \n  <a href=\"https://mcf.indianrailways.gov.in/uploads/%E0%A4%AA%E0%A5%8D%E0%A4%B0%E0%A4%97%E0%A4%A4%E0%A4%BF%20%E0%A4%AA%E0%A4%A4%E0%A5%8D%E0%A4%B0%E0%A4%BF%E0%A4%95%E0%A4%BE%20%E0%A4%B8%E0%A4%BF%E0%A4%A4%E0%A4%AE%E0%A5%8D%E0%A4%AC%E0%A4%B0%202025.pdf\" target=\"_blank\" rel=\"noopener noreferrer\" class=\"rajbhasha-card\">\n    <div class=\"rajbhasha-icon\">📄</div>\n    <div class=\"rajbhasha-content\">\n      <strong>Pragati Patrika September 2025</strong>\n    </div>\n    <span class=\"rajbhasha-arrow\">→</span>\n  </a>\n  \n  <a href=\"https://mcf.indianrailways.gov.in/uploads/files/1767851143566-pragati%20file.pdf\" target=\"_blank\" rel=\"noopener noreferrer\" class=\"rajbhasha-card\">\n    <div class=\"rajbhasha-icon\">📄</div>\n    <div class=\"rajbhasha-content\">\n      <strong>Pragati Patrika December 2025</strong>\n    </div>\n    <span class=\"rajbhasha-arrow\">→</span>\n  </a>\n  \n  <a href=\"https://mcf.indianrailways.gov.in/uploads/%E0%A4%B8%E0%A4%82%E0%A4%98%20%E0%A4%95%E0%A4%BE%20%E0%A4%B0%E0%A4%BE%E0%A4%9C%E0%A4%95%E0%A5%80%E0%A4%AF%20%E0%A4%95%E0%A4%BE%E0%A4%B0%E0%A5%8D%E0%A4%AF%20%E0%A4%B9%E0%A4%BF%E0%A4%82%E0%A4%A6%E0%A5%80%20%E0%A4%AE%E0%A5%87%E0%A4%82%20%E0%A4%95%E0%A4%B0%E0%A4%A8%E0%A5%87%20%E0%A4%B9%E0%A5%87%E0%A4%A4%E0%A5%81%20%E0%A4%B5%E0%A4%BE%E0%A4%B0%E0%A5%8D%E0%A4%B7%E0%A4%BF%E0%A4%95%20%E0%A4%95%E0%A4%BE%E0%A4%B0%E0%A5%8D%E0%A4%AF%E0%A4%95%E0%A5%8D%E0%A4%B0%E0%A4%AE%202025-26.pdf\" target=\"_blank\" rel=\"noopener noreferrer\" class=\"rajbhasha-card\">\n    <div class=\"rajbhasha-icon\">📄</div>\n    <div class=\"rajbhasha-content\">\n      <strong>ANNUAL PROGRAMME FOR TRANSACTING THE OFFICIAL WORK OF THE UNION IN HINDI 2025-26</strong>\n    </div>\n    <span class=\"rajbhasha-arrow\">→</span>\n  </a>\n  \n  <a href=\"https://mcf.indianrailways.gov.in/uploads/%E0%A4%95%E0%A4%BF%E0%A4%A4%E0%A4%BE%E0%A4%AC%E0%A5%8B%E0%A4%82%20%E0%A4%95%E0%A5%80%20%E0%A4%B8%E0%A5%82%E0%A4%9A%E0%A5%80.pdf\" target=\"_blank\" rel=\"noopener noreferrer\" class=\"rajbhasha-card\">\n    <div class=\"rajbhasha-icon\">📄</div>\n    <div class=\"rajbhasha-content\">\n      <strong>Library Book List</strong>\n    </div>\n    <span class=\"rajbhasha-arrow\">→</span>\n  </a>\n  \n  <a href=\"http://10.211.12.102:8080/lmsmcf/index.jsp\" target=\"_blank\" rel=\"noopener noreferrer\" class=\"rajbhasha-card\">\n    <div class=\"rajbhasha-icon\">🔗</div>\n    <div class=\"rajbhasha-content\">\n      <strong>Library Portal Link</strong>\n    </div>\n    <span class=\"rajbhasha-arrow\">→</span>\n  </a>\n  <p style=\"font-size: 0.75rem; color: #64748b; margin-top: 0.5rem;\">(Accessible only in LAN of MCF)</p>\n</div>",
  "contentMarkdown": "[Rajbhasha Niti](https://mcf.indianrailways.gov.in/works/uploads/File/Rajbhasha%20Niti%202018-19\\(1\\).pdf)\n\n[Pratibimb Railway Booklet-1](https://mcf.indianrailways.gov.in/uploads/files/September%202019.pdf)\n\n[Pratibimb Railway Booklet-2](https://mcf.indianrailways.gov.in/uploads/files/September%202020.pdf)\n\n[Pragati Patrika](https://mcf.indianrailways.gov.in/uploads/%E0%A4%AA%E0%A5%8D%E0%A4%B0%E0%A4%97%E0%A4%A4%E0%A4%BF%20%E0%A4%AA%E0%A4%A4%E0%A5%8D%E0%A4%B0%E0%A4%BF%E0%A4%95%E0%A4%BE%20%E0%A4%B8%E0%A4%BF%E0%A4%A4%E0%A4%82%E0%A4%AC%E0%A4%B0%202024.pdf)\n\n[Pragati patrika June 2024](https://mcf.indianrailways.gov.in/uploads/MCF%20Pragati%20June-24.pdf)\n\n[Pragati patrika Dec 2024](https://mcf.indianrailways.gov.in/uploads/%E0%A4%AA%E0%A5%8D%E0%A4%B0%E0%A4%97%E0%A4%A4%E0%A4%BF%20%E0%A4%AA%E0%A4%A4%E0%A5%8D%E0%A4%B0%E0%A4%BF%E0%A4%95%E0%A4%BE%20%20%E0%A4%A6%E0%A4%BF%E0%A4%B8%E0%A4%82%E0%A4%AC%E0%A4%B0-2024.pdf)\n\n[Pragati patrika March 2025](https://mcf.indianrailways.gov.in/uploads/%E0%A4%AE%E0%A4%BE%E0%A4%B0%E0%A5%8D%E0%A4%9A-2025%20%E0%A4%AA%E0%A5%8D%E0%A4%B0%E0%A4%97%E0%A4%A4%E0%A4%BF%20%E0%A4%AA%E0%A4%A4%E0%A5%8D%E0%A4%B0%E0%A4%BF%E0%A4%95%E0%A4%BE\\(1\\).pdf)\n\n[Pragati patrika June 2025](https://mcf.indianrailways.gov.in/uploads/%E0%A4%AA%E0%A5%8D%E0%A4%B0%E0%A4%97%E0%A4%A4%E0%A4%BF%20%E0%A4%AA%E0%A4%A4%E0%A5%8D%E0%A4%B0%E0%A4%BF%E0%A4%95%E0%A4%BE%20%E0%A4%9C%E0%A5%82%E0%A4%A8-2025.pdf)\n\n[Pragati Patrika September 2025](https://mcf.indianrailways.gov.in/uploads/%E0%A4%AA%E0%A5%8D%E0%A4%B0%E0%A4%97%E0%A4%A4%E0%A4%BF%20%E0%A4%AA%E0%A4%A4%E0%A5%8D%E0%A4%B0%E0%A4%BF%E0%A4%95%E0%A4%BE%20%E0%A4%B8%E0%A4%BF%E0%A4%A4%E0%A4%AE%E0%A5%8D%E0%A4%AC%E0%A4%B0%202025.pdf)\n\n[Pragati Patrika December 2025](https://mcf.indianrailways.gov.in/uploads/files/1767851143566-pragati%20file.pdf)\n\n[ANNUAL PROGRAMME FOR TRANSACTING THE OFFICIAL WORK OF THE UNION IN HINDI 2025-26](https://mcf.indianrailways.gov.in/uploads/%E0%A4%B8%E0%A4%82%E0%A4%98%20%E0%A4%95%E0%A4%BE%20%E0%A4%B0%E0%A4%BE%E0%A4%9C%E0%A4%95%E0%A5%80%E0%A4%AF%20%E0%A4%95%E0%A4%BE%E0%A4%B0%E0%A5%8D%E0%A4%AF%20%E0%A4%B9%E0%A4%BF%E0%A4%82%E0%A4%A6%E0%A5%80%20%E0%A4%AE%E0%A5%87%E0%A4%82%20%E0%A4%95%E0%A4%B0%E0%A4%A8%E0%A5%87%20%E0%A4%B9%E0%A5%87%E0%A4%A4%E0%A5%81%20%E0%A4%B5%E0%A4%BE%E0%A4%B0%E0%A5%8D%E0%A4%B7%E0%A4%BF%E0%A4%95%20%E0%A4%95%E0%A4%BE%E0%A4%B0%E0%A5%8D%E0%A4%AF%E0%A4%95%E0%A5%8D%E0%A4%B0%E0%A4%AE%202025-26.pdf)\n\n[Library Book List](https://mcf.indianrailways.gov.in/uploads/%E0%A4%95%E0%A4%BF%E0%A4%A4%E0%A4%BE%E0%A4%AC%E0%A5%8B%E0%A4%82%20%E0%A4%95%E0%A5%80%20%E0%A4%B8%E0%A5%82%E0%A4%9A%E0%A5%80.pdf)\n\n[Library Portal Link](http://10.211.12.102:8080/lmsmcf/index.jsp) (Accessible only in LAN of MCF)",
  "tables": [],
  "images": [],
  "attachments": []
}

