{
  "id": "0,298,729,765",
  "slug": "department/general-administration/contact-details",
  "title": "Contact Details",
  "lang": "en",
  "lastReviewed": null,
  "contentHtml": "<p align=\"justify\"></p><p>\n\t<strong>Contact Details</strong></p>\n<table align=\"center\" border=\"1\" cellpadding=\"0\" width=\"605\">\n\t\n\t\t<tr>\n\t\t\t<td>\n\t\t\t\t<p>\n\t\t\t\t\t<strong>S.No</strong></p>\n\t\t\t</td>\n\t\t\t<td>\n\t\t\t\t<p align=\"center\">\n\t\t\t\t\t<strong>Designation</strong></p>\n\t\t\t</td>\n\t\t\t<td>\n\t\t\t\t<p align=\"center\">\n\t\t\t\t\t<strong>Rly. No</strong></p>\n\t\t\t</td>\n\t\t\t<td>\n\t\t\t\t<p align=\"center\">\n\t\t\t\t\t<strong>DOT</strong></p>\n\t\t\t</td>\n\t\t\t<td>\n\t\t\t\t<p align=\"center\">\n\t\t\t\t\t<strong>FAX</strong></p>\n\t\t\t</td>\n\t\t\t<td>\n\t\t\t\t<p align=\"center\">\n\t\t\t\t\t<strong>E-Mail ID</strong></p>\n\t\t\t</td>\n\t\t\t<td>\n\t\t\t\t<p align=\"center\">\n\t\t\t\t\t<strong>CUG No.</strong></p>\n\t\t\t</td>\n\t\t</tr>\n\t\t<tr>\n\t\t\t<td>\n\t\t\t\t<p align=\"center\">\n\t\t\t\t\t1</p>\n\t\t\t</td>\n\t\t\t<td>\n\t\t\t\t<p align=\"center\">\n\t\t\t\t\tSecy. to GM &amp; CPRO</p>\n\t\t\t</td>\n\t\t\t<td>\n\t\t\t\t<p align=\"center\">\n\t\t\t\t\t60001</p>\n\t\t\t</td>\n\t\t\t<td>\n\t\t\t\t<p align=\"center\">\n\t\t\t\t\t2704370</p>\n\t\t\t</td>\n\t\t\t<td>\n\t\t\t\t<p align=\"center\">\n\t\t\t\t\t2704376</p>\n\t\t\t</td>\n\t\t\t<td>\n\t\t\t\t<p align=\"center\">\n\t\t\t\t\t<a class=\"linkn\" href=\"mailto:secretary@rcfrbl.railnet.gov.in\">secretary@rcfrbl.railnet.gov.in</a></p>\n\t\t\t\t<p align=\"center\">\n\t\t\t\t\t<a class=\"linkn\" href=\"mailto:cpromcfrbl@gmail.com\">cpromcfrbl@gmail.com</a></p>\n\t\t\t</td>\n\t\t\t<td>\n\t\t\t\t<p align=\"center\">\n\t\t\t\t\t7318060002</p>\n\t\t\t</td>\n\t\t</tr>\n\t\t<tr>\n\t\t\t<td>\n\t\t\t\t2</td>\n\t\t\t<td>\n\t\t\t\tDy.GM/G</td>\n\t\t\t<td>\n\t\t\t\t60002</td>\n\t\t\t<td>\n\t\t\t\t2704341</td>\n\t\t\t<td>\n\t\t\t\t2704325</td>\n\t\t\t<td>\n\t\t\t\t<a class=\"linkn\" href=\"http://dgmmcfrbl@gmail.com/\">dgmmcfrbl@gmail.com</a></td>\n\t\t\t<td>\n\t\t\t\t7318060421</td>\n\t\t</tr>\n\t\t<tr>\n\t\t\t<td>\n\t\t\t\t<p align=\"center\">\n\t\t\t\t\t3</p>\n\t\t\t</td>\n\t\t\t<td>\n\t\t\t\t<p align=\"center\">\n\t\t\t\t\tPS-I to GM &amp; PRO</p>\n\t\t\t</td>\n\t\t\t<td>\n\t\t\t\t<p align=\"center\">\n\t\t\t\t\t60010</p>\n\t\t\t</td>\n\t\t\t<td>\n\t\t\t\t<p align=\"center\">\n\t\t\t\t\t2704365</p>\n\t\t\t</td>\n\t\t\t<td>\n\t\t\t\t<p align=\"center\">\n\t\t\t\t\t2704311</p>\n\t\t\t</td>\n\t\t\t<td>\n\t\t\t\t<p align=\"center\">\n\t\t\t\t\t<a class=\"linkn\" href=\"mailto:pstogmrcfrbl@gmail.com\">pstogmrcfrbl@gmail.com</a></p>\n\t\t\t\t<p align=\"center\">\n\t\t\t\t\t<a class=\"linkn\" href=\"mailto:promcfrbl@gmail.com\">promcfrbl@gmail.com</a></p>\n\t\t\t</td>\n\t\t\t<td>\n\t\t\t\t<p align=\"center\">\n\t\t\t\t\t&nbsp;7318060012</p>\n\t\t\t</td>\n\t\t</tr>\n\t\t<tr>\n\t\t\t<td>\n\t\t\t\t<p align=\"center\">\n\t\t\t\t\t4</p>\n\t\t\t</td>\n\t\t\t<td>\n\t\t\t\t<p align=\"center\">\n\t\t\t\t\tAsst. Secy/ Confidential</p>\n\t\t\t</td>\n\t\t\t<td>\n\t\t\t\t<p align=\"center\">\n\t\t\t\t\t60005</p>\n\t\t\t</td>\n\t\t\t<td>\n\t\t\t\t<p align=\"center\">\n\t\t\t\t\t-</p>\n\t\t\t</td>\n\t\t\t<td>\n\t\t\t\t<p align=\"center\">\n\t\t\t\t\t--</p>\n\t\t\t</td>\n\t\t\t<td>\n\t\t\t\t<p align=\"center\">\n\t\t\t\t\t<a class=\"linkn\" href=\"http://rakesh.rajan77@gov.in/\">rakesh.rajan77@gov.in</a></p>\n\t\t\t</td>\n\t\t\t<td>\n\t\t\t\t<p align=\"center\">\n\t\t\t\t\t&nbsp;7318060232</p>\n\t\t\t</td>\n\t\t</tr>\n\t\t<tr>\n\t\t\t<td>\n\t\t\t\t<p align=\"center\">\n\t\t\t\t\t5</p>\n\t\t\t</td>\n\t\t\t<td>\n\t\t\t\t<p align=\"center\">\n\t\t\t\t\tADGM</p>\n\t\t\t</td>\n\t\t\t<td>\n\t\t\t\t<p align=\"center\">\n\t\t\t\t\t60013</p>\n\t\t\t</td>\n\t\t\t<td>\n\t\t\t\t<p align=\"center\">\n\t\t\t\t\t--</p>\n\t\t\t</td>\n\t\t\t<td>\n\t\t\t\t<p align=\"center\">\n\t\t\t\t\t--</p>\n\t\t\t</td>\n\t\t\t<td>\n\t\t\t\t<p align=\"center\">\n\t\t\t\t\t<a class=\"linkn\" href=\"mailto:adgmmcfrbl@gmail.com\">adgmmcfrbl@gmail.com</a></p>\n\t\t\t</td>\n\t\t\t<td>\n\t\t\t\t<p align=\"center\">\n\t\t\t\t\t&nbsp;7318060011</p>\n\t\t\t</td>\n\t\t</tr>\n\t\n</table>\n<p>\n\t&nbsp;</p>\n<p></p>\n\t\t\t\t\t\t\t\t\t<br>",
  "contentMarkdown": "**Contact Details**\n\n**S.No**\n\n**Designation**\n\n**Rly. No**\n\n**DOT**\n\n**FAX**\n\n**E-Mail ID**\n\n**CUG No.**\n\n1\n\nSecy. to GM & CPRO\n\n60001\n\n2704370\n\n2704376\n\n[secretary@rcfrbl.railnet.gov.in](mailto:secretary@rcfrbl.railnet.gov.in)\n\n[cpromcfrbl@gmail.com](mailto:cpromcfrbl@gmail.com)\n\n7318060002\n\n2\n\nDy.GM/G\n\n60002\n\n2704341\n\n2704325\n\n[dgmmcfrbl@gmail.com](http://dgmmcfrbl@gmail.com/)\n\n7318060421\n\n3\n\nPS-I to GM & PRO\n\n60010\n\n2704365\n\n2704311\n\n[pstogmrcfrbl@gmail.com](mailto:pstogmrcfrbl@gmail.com)\n\n[promcfrbl@gmail.com](mailto:promcfrbl@gmail.com)\n\n 7318060012\n\n4\n\nAsst. Secy/ Confidential\n\n60005\n\n\\-\n\n\\--\n\n[rakesh.rajan77@gov.in](http://rakesh.rajan77@gov.in/)\n\n 7318060232\n\n5\n\nADGM\n\n60013\n\n\\--\n\n\\--\n\n[adgmmcfrbl@gmail.com](mailto:adgmmcfrbl@gmail.com)\n\n 7318060011",
  "tables": [
    {
      "headers": [
        "S.No",
        "Designation",
        "Rly. No",
        "DOT",
        "FAX",
        "E-Mail ID",
        "CUG No."
      ],
      "rows": [
        [
          "1",
          "Secy. to GM & CPRO",
          "60001",
          "2704370",
          "2704376",
          "secretary@rcfrbl.railnet.gov.in cpromcfrbl@gmail.com",
          "7318060002"
        ],
        [
          "2",
          "Dy.GM/G",
          "60002",
          "2704341",
          "2704325",
          "dgmmcfrbl@gmail.com",
          "7318060421"
        ],
        [
          "3",
          "PS-I to GM & PRO",
          "60010",
          "2704365",
          "2704311",
          "pstogmrcfrbl@gmail.com promcfrbl@gmail.com",
          "7318060012"
        ],
        [
          "4",
          "Asst. Secy/ Confidential",
          "60005",
          "-",
          "--",
          "rakesh.rajan77@gov.in",
          "7318060232"
        ],
        [
          "5",
          "ADGM",
          "60013",
          "--",
          "--",
          "adgmmcfrbl@gmail.com",
          "7318060011"
        ]
      ]
    }
  ],
  "images": [],
  "attachments": []
}
